deliberate/__init__.py
deliberate/__main__.py
deliberate/agent_context.py
deliberate/agent_detection.py
deliberate/artifacts.py
deliberate/cli.py
deliberate/config.py
deliberate/constants.py
deliberate/maintenance.py
deliberate/mcp_orchestrator_server.py
deliberate/orchestrator.py
deliberate/review_tui.py
deliberate/settings.py
deliberate/types.py
deliberate/verbose_logger.py
deliberate/visualization.py
deliberate/adapters/__init__.py
deliberate/adapters/api_adapter.py
deliberate/adapters/base.py
deliberate/adapters/cli_adapter.py
deliberate/adapters/fake_adapter.py
deliberate/adapters/mcp_adapter.py
deliberate/budget/__init__.py
deliberate/budget/tracker.py
deliberate/context/__init__.py
deliberate/evolution/__init__.py
deliberate/evolution/adversarial.py
deliberate/evolution/controller.py
deliberate/evolution/database.py
deliberate/evolution/diff_evolution.py
deliberate/evolution/evaluator.py
deliberate/evolution/prompt_builder.py
deliberate/evolution/test_evaluator.py
deliberate/evolution/test_prompt_builder.py
deliberate/evolution/types.py
deliberate/git/__init__.py
deliberate/git/branch_workflow.py
deliberate/git/virtual_worktree.py
deliberate/git/worktree.py
deliberate/github/__init__.py
deliberate/github/actions.py
deliberate/github/bot.py
deliberate/github/client.py
deliberate/github/handler.py
deliberate/iteration/__init__.py
deliberate/iteration/evaluators.py
deliberate/iteration/extractors.py
deliberate/iteration/feedback.py
deliberate/iteration/history.py
deliberate/iteration/solver.py
deliberate/iteration/types.py
deliberate/mcp_server/__init__.py
deliberate/mcp_server/routing.py
deliberate/mcp_server/state.py
deliberate/phases/__init__.py
deliberate/phases/evolution.py
deliberate/phases/execution.py
deliberate/phases/planning.py
deliberate/phases/refinement.py
deliberate/phases/review.py
deliberate/prompts/__init__.py
deliberate/prompts/execution.py
deliberate/prompts/planning.py
deliberate/prompts/review.py
deliberate/review/__init__.py
deliberate-0.1.2.dist-info/METADATA
deliberate-0.1.2.dist-info/WHEEL
deliberate-0.1.2.dist-info/entry_points.txt
deliberate-0.1.2.dist-info/licenses/LICENSE
deliberate-0.1.2.dist-info/RECORD
