Metadata-Version: 2.4
Name: deliberate
Version: 0.1.2
Summary: Multi-LLM ensemble orchestrator for code generation and review
Project-URL: Homepage, https://github.com/hardbyte/deliberate
Project-URL: Repository, https://github.com/hardbyte/deliberate
Project-URL: Issues, https://github.com/hardbyte/deliberate/issues
License: MIT
License-File: LICENSE
Requires-Python: >=3.11
Requires-Dist: duckdb>=1.0.0
Requires-Dist: genai-prices>=0.0.47
Requires-Dist: httpx>=0.25.0
Requires-Dist: json-repair>=0.54.2
Requires-Dist: litellm>=1.80.7
Requires-Dist: mcp>=1.22.0
Requires-Dist: platformdirs>=4.0.0
Requires-Dist: pydantic-settings>=2.0.0
Requires-Dist: pydantic>=2.0.0
Requires-Dist: pyyaml>=6.0
Requires-Dist: rich>=13.0.0
Requires-Dist: typer>=0.9.0
Provides-Extra: all
Requires-Dist: mkdocs>=1.6.0; extra == 'all'
Requires-Dist: opentelemetry-api>=1.20.0; extra == 'all'
Requires-Dist: opentelemetry-exporter-otlp>=1.20.0; extra == 'all'
Requires-Dist: opentelemetry-instrumentation>=0.41b0; extra == 'all'
Requires-Dist: opentelemetry-sdk>=1.20.0; extra == 'all'
Requires-Dist: pytest-asyncio>=0.21.0; extra == 'all'
Requires-Dist: pytest-timeout>=2.2.0; extra == 'all'
Requires-Dist: pytest>=7.0.0; extra == 'all'
Requires-Dist: ruff>=0.1.0; extra == 'all'
Provides-Extra: dev
Requires-Dist: pytest-asyncio>=0.21.0; extra == 'dev'
Requires-Dist: pytest-timeout>=2.2.0; extra == 'dev'
Requires-Dist: pytest>=7.0.0; extra == 'dev'
Requires-Dist: ruff>=0.1.0; extra == 'dev'
Provides-Extra: docs
Requires-Dist: mkdocs>=1.6.0; extra == 'docs'
Provides-Extra: tracing
Requires-Dist: opentelemetry-api>=1.20.0; extra == 'tracing'
Requires-Dist: opentelemetry-exporter-otlp>=1.20.0; extra == 'tracing'
Requires-Dist: opentelemetry-instrumentation>=0.41b0; extra == 'tracing'
Requires-Dist: opentelemetry-sdk>=1.20.0; extra == 'tracing'
